<annotation>
	<folder>catchup-oderich</folder>
	<filename>20200611_173922.jpg</filename>
	<path>/run/media/iriordmb/MULTIBOOT/DataSetTCC/catchup-oderich/20200611_173922.jpg</path>
	<source>
		<database>Unknown</database>
	</source>
	<size>
		<width>4160</width>
		<height>3120</height>
		<depth>3</depth>
	</size>
	<segmented>0</segmented>
	<object>
		<name>catchup-oderich</name>
		<pose>Unspecified</pose>
		<truncated>0</truncated>
		<difficult>0</difficult>
		<bndbox>
			<xmin>597</xmin>
			<ymin>717</ymin>
			<xmax>3242</xmax>
			<ymax>2522</ymax>
		</bndbox>
	</object>
</annotation>
